MachaTheKing/__init__.py
MachaTheKing/christmas.py
MachaTheKing/conversation.py
MachaTheKing/our_ascii.py
MachaTheKing/xmas.py
MachaTheKing/xmas_turtle.py
MachaTheKing/static/jinglebells.mp3
secret_santa/__init__.py
secret_santa/christmas.py
secret_santa/conversation.py
secret_santa/our_ascii.py
secret_santa/xmas.py
secret_santa/xmas_turtle.py
static/__init__.py
static/jinglebells.mp3
MachaTheKing-99.99.99.dist-info/LICENCE.txt
MachaTheKing-99.99.99.dist-info/METADATA
MachaTheKing-99.99.99.dist-info/WHEEL
MachaTheKing-99.99.99.dist-info/top_level.txt
MachaTheKing-99.99.99.dist-info/RECORD
