Metadata-Version: 2.1
Name: MachaTheKing
Version: 99.99.99
Summary: A Simple Secret santa surprise
Author: Mr Smart boy
Author-email: snagavamsi123@gmail.com
License: UNKNOWN
Platform: UNKNOWN
Classifier: Programming Language :: Python :: 3
Classifier: License :: OSI Approved :: MIT License
Classifier: Operating System :: OS Independent
License-File: LICENCE.txt
Requires-Dist: termcolor
Requires-Dist: tkintertable
Requires-Dist: colorama
Requires-Dist: playsound
Requires-Dist: pygame
